README.md
setup.py
oren_pack_try/__init__.py
oren_pack_try/adder.py
oren_pack_try/adder_prin.py
oren_pack_try.egg-info/PKG-INFO
oren_pack_try.egg-info/SOURCES.txt
oren_pack_try.egg-info/dependency_links.txt
oren_pack_try.egg-info/not-zip-safe
oren_pack_try.egg-info/top_level.txt