Metadata-Version: 1.0
Name: oren-pack-try
Version: 0.1
Summary: oren_pack_try
Home-page: UNKNOWN
Author: UNKNOWN
Author-email: UNKNOWN
License: UNKNOWN
Platform: UNKNOWN
